{
  "schema_version": "1.0.0",
  "language_code": "en",
  "relationship_category": "morphological",
  "count": 232,
  "relationships": [
    {
      "source_lexical_form": "be",
      "target_lexical_form": "am",
      "relationship_kind": "FIRST_PERSON_FORM"
    },
    {
      "source_lexical_form": "be",
      "target_lexical_form": "is",
      "relationship_kind": "THIRD_PERSON_FORM"
    },
    {
      "source_lexical_form": "be",
      "target_lexical_form": "are",
      "relationship_kind": "SECOND_PERSON_FORM"
    },
    {
      "source_lexical_form": "be",
      "target_lexical_form": "was",
      "relationship_kind": "PAST_TENSE_FORM"
    },
    {
      "source_lexical_form": "be",
      "target_lexical_form": "were",
      "relationship_kind": "PAST_TENSE_FORM"
    },
    {
      "source_lexical_form": "be",
      "target_lexical_form": "been",
      "relationship_kind": "PAST_PARTICIPLE_FORM"
    },
    {
      "source_lexical_form": "be",
      "target_lexical_form": "being",
      "relationship_kind": "PRESENT_PARTICIPLE_FORM"
    },
    {
      "source_lexical_form": "have",
      "target_lexical_form": "has",
      "relationship_kind": "THIRD_PERSON_FORM"
    },
    {
      "source_lexical_form": "have",
      "target_lexical_form": "had",
      "relationship_kind": "PAST_TENSE_FORM"
    },
    {
      "source_lexical_form": "have",
      "target_lexical_form": "having",
      "relationship_kind": "PRESENT_PARTICIPLE_FORM"
    },
    {
      "source_lexical_form": "do",
      "target_lexical_form": "does",
      "relationship_kind": "THIRD_PERSON_FORM"
    },
    {
      "source_lexical_form": "do",
      "target_lexical_form": "did",
      "relationship_kind": "PAST_TENSE_FORM"
    },
    {
      "source_lexical_form": "this",
      "target_lexical_form": "these",
      "relationship_kind": "PLURAL_FORM"
    },
    {
      "source_lexical_form": "that",
      "target_lexical_form": "those",
      "relationship_kind": "PLURAL_FORM"
    },
    {
      "source_lexical_form": "few",
      "target_lexical_form": "fewer",
      "relationship_kind": "COMPARATIVE_FORM"
    },
    {
      "source_lexical_form": "many",
      "target_lexical_form": "more",
      "relationship_kind": "COMPARATIVE_FORM"
    },
    {
      "source_lexical_form": "many",
      "target_lexical_form": "most",
      "relationship_kind": "SUPERLATIVE_FORM"
    },
    {
      "source_lexical_form": "much",
      "target_lexical_form": "more",
      "relationship_kind": "COMPARATIVE_FORM"
    },
    {
      "source_lexical_form": "much",
      "target_lexical_form": "most",
      "relationship_kind": "SUPERLATIVE_FORM"
    },
    {
      "source_lexical_form": "I",
      "target_lexical_form": "me",
      "relationship_kind": "PRONOUN_OBJECT_FORM"
    },
    {
      "source_lexical_form": "I",
      "target_lexical_form": "my",
      "relationship_kind": "PRONOUN_POSSESSIVE_DETERMINER_FORM"
    },
    {
      "source_lexical_form": "I",
      "target_lexical_form": "mine",
      "relationship_kind": "PRONOUN_POSSESSIVE_FORM"
    },
    {
      "source_lexical_form": "I",
      "target_lexical_form": "myself",
      "relationship_kind": "PRONOUN_REFLEXIVE_FORM"
    },
    {
      "source_lexical_form": "you",
      "target_lexical_form": "your",
      "relationship_kind": "PRONOUN_POSSESSIVE_DETERMINER_FORM"
    },
    {
      "source_lexical_form": "you",
      "target_lexical_form": "yours",
      "relationship_kind": "PRONOUN_POSSESSIVE_FORM"
    },
    {
      "source_lexical_form": "you",
      "target_lexical_form": "yourself",
      "relationship_kind": "PRONOUN_REFLEXIVE_FORM"
    },
    {
      "source_lexical_form": "you",
      "target_lexical_form": "yourselves",
      "relationship_kind": "PRONOUN_REFLEXIVE_FORM"
    },
    {
      "source_lexical_form": "he",
      "target_lexical_form": "him",
      "relationship_kind": "PRONOUN_OBJECT_FORM"
    },
    {
      "source_lexical_form": "he",
      "target_lexical_form": "his",
      "relationship_kind": "PRONOUN_POSSESSIVE_DETERMINER_FORM"
    },
    {
      "source_lexical_form": "he",
      "target_lexical_form": "himself",
      "relationship_kind": "PRONOUN_REFLEXIVE_FORM"
    },
    {
      "source_lexical_form": "she",
      "target_lexical_form": "her",
      "relationship_kind": "PRONOUN_OBJECT_FORM"
    },
    {
      "source_lexical_form": "she",
      "target_lexical_form": "her",
      "relationship_kind": "PRONOUN_POSSESSIVE_DETERMINER_FORM"
    },
    {
      "source_lexical_form": "she",
      "target_lexical_form": "hers",
      "relationship_kind": "PRONOUN_POSSESSIVE_FORM"
    },
    {
      "source_lexical_form": "she",
      "target_lexical_form": "herself",
      "relationship_kind": "PRONOUN_REFLEXIVE_FORM"
    },
    {
      "source_lexical_form": "it",
      "target_lexical_form": "its",
      "relationship_kind": "PRONOUN_POSSESSIVE_DETERMINER_FORM"
    },
    {
      "source_lexical_form": "it",
      "target_lexical_form": "itself",
      "relationship_kind": "PRONOUN_REFLEXIVE_FORM"
    },
    {
      "source_lexical_form": "we",
      "target_lexical_form": "us",
      "relationship_kind": "PRONOUN_OBJECT_FORM"
    },
    {
      "source_lexical_form": "we",
      "target_lexical_form": "our",
      "relationship_kind": "PRONOUN_POSSESSIVE_DETERMINER_FORM"
    },
    {
      "source_lexical_form": "we",
      "target_lexical_form": "ours",
      "relationship_kind": "PRONOUN_POSSESSIVE_FORM"
    },
    {
      "source_lexical_form": "we",
      "target_lexical_form": "ourselves",
      "relationship_kind": "PRONOUN_REFLEXIVE_FORM"
    },
    {
      "source_lexical_form": "they",
      "target_lexical_form": "them",
      "relationship_kind": "PRONOUN_OBJECT_FORM"
    },
    {
      "source_lexical_form": "they",
      "target_lexical_form": "their",
      "relationship_kind": "PRONOUN_POSSESSIVE_DETERMINER_FORM"
    },
    {
      "source_lexical_form": "they",
      "target_lexical_form": "theirs",
      "relationship_kind": "PRONOUN_POSSESSIVE_FORM"
    },
    {
      "source_lexical_form": "they",
      "target_lexical_form": "themselves",
      "relationship_kind": "PRONOUN_REFLEXIVE_FORM"
    },
    {
      "source_lexical_form": "do",
      "target_lexical_form": "done",
      "relationship_kind": "PAST_PARTICIPLE_FORM"
    },
    {
      "source_lexical_form": "do",
      "target_lexical_form": "doing",
      "relationship_kind": "PRESENT_PARTICIPLE_FORM"
    },
    {
      "source_lexical_form": "few",
      "target_lexical_form": "fewest",
      "relationship_kind": "SUPERLATIVE_FORM"
    },
    {
      "source_lexical_form": "little",
      "target_lexical_form": "less",
      "relationship_kind": "COMPARATIVE_FORM"
    },
    {
      "source_lexical_form": "little",
      "target_lexical_form": "least",
      "relationship_kind": "SUPERLATIVE_FORM"
    },
    {
      "source_lexical_form": "am",
      "target_lexical_form": "be",
      "relationship_kind": "LEMMA_FORM"
    },
    {
      "source_lexical_form": "is",
      "target_lexical_form": "be",
      "relationship_kind": "LEMMA_FORM"
    },
    {
      "source_lexical_form": "are",
      "target_lexical_form": "be",
      "relationship_kind": "LEMMA_FORM"
    },
    {
      "source_lexical_form": "was",
      "target_lexical_form": "be",
      "relationship_kind": "LEMMA_FORM"
    },
    {
      "source_lexical_form": "were",
      "target_lexical_form": "be",
      "relationship_kind": "LEMMA_FORM"
    },
    {
      "source_lexical_form": "been",
      "target_lexical_form": "be",
      "relationship_kind": "LEMMA_FORM"
    },
    {
      "source_lexical_form": "being",
      "target_lexical_form": "be",
      "relationship_kind": "LEMMA_FORM"
    },
    {
      "source_lexical_form": "has",
      "target_lexical_form": "have",
      "relationship_kind": "LEMMA_FORM"
    },
    {
      "source_lexical_form": "had",
      "target_lexical_form": "have",
      "relationship_kind": "LEMMA_FORM"
    },
    {
      "source_lexical_form": "having",
      "target_lexical_form": "have",
      "relationship_kind": "LEMMA_FORM"
    },
    {
      "source_lexical_form": "does",
      "target_lexical_form": "do",
      "relationship_kind": "LEMMA_FORM"
    },
    {
      "source_lexical_form": "did",
      "target_lexical_form": "do",
      "relationship_kind": "LEMMA_FORM"
    },
    {
      "source_lexical_form": "these",
      "target_lexical_form": "this",
      "relationship_kind": "LEMMA_FORM"
    },
    {
      "source_lexical_form": "those",
      "target_lexical_form": "that",
      "relationship_kind": "LEMMA_FORM"
    },
    {
      "source_lexical_form": "fewer",
      "target_lexical_form": "few",
      "relationship_kind": "LEMMA_FORM"
    },
    {
      "source_lexical_form": "more",
      "target_lexical_form": "many",
      "relationship_kind": "LEMMA_FORM"
    },
    {
      "source_lexical_form": "most",
      "target_lexical_form": "many",
      "relationship_kind": "LEMMA_FORM"
    },
    {
      "source_lexical_form": "more",
      "target_lexical_form": "much",
      "relationship_kind": "LEMMA_FORM"
    },
    {
      "source_lexical_form": "most",
      "target_lexical_form": "much",
      "relationship_kind": "LEMMA_FORM"
    },
    {
      "source_lexical_form": "me",
      "target_lexical_form": "I",
      "relationship_kind": "PRONOUN_SUBJECT_FORM"
    },
    {
      "source_lexical_form": "my",
      "target_lexical_form": "I",
      "relationship_kind": "LEMMA_FORM"
    },
    {
      "source_lexical_form": "mine",
      "target_lexical_form": "I",
      "relationship_kind": "LEMMA_FORM"
    },
    {
      "source_lexical_form": "myself",
      "target_lexical_form": "I",
      "relationship_kind": "LEMMA_FORM"
    },
    {
      "source_lexical_form": "your",
      "target_lexical_form": "you",
      "relationship_kind": "LEMMA_FORM"
    },
    {
      "source_lexical_form": "yours",
      "target_lexical_form": "you",
      "relationship_kind": "LEMMA_FORM"
    },
    {
      "source_lexical_form": "yourself",
      "target_lexical_form": "you",
      "relationship_kind": "LEMMA_FORM"
    },
    {
      "source_lexical_form": "yourselves",
      "target_lexical_form": "you",
      "relationship_kind": "LEMMA_FORM"
    },
    {
      "source_lexical_form": "him",
      "target_lexical_form": "he",
      "relationship_kind": "PRONOUN_SUBJECT_FORM"
    },
    {
      "source_lexical_form": "his",
      "target_lexical_form": "he",
      "relationship_kind": "LEMMA_FORM"
    },
    {
      "source_lexical_form": "himself",
      "target_lexical_form": "he",
      "relationship_kind": "LEMMA_FORM"
    },
    {
      "source_lexical_form": "her",
      "target_lexical_form": "she",
      "relationship_kind": "PRONOUN_SUBJECT_FORM"
    },
    {
      "source_lexical_form": "her",
      "target_lexical_form": "she",
      "relationship_kind": "LEMMA_FORM"
    },
    {
      "source_lexical_form": "hers",
      "target_lexical_form": "she",
      "relationship_kind": "LEMMA_FORM"
    },
    {
      "source_lexical_form": "herself",
      "target_lexical_form": "she",
      "relationship_kind": "LEMMA_FORM"
    },
    {
      "source_lexical_form": "its",
      "target_lexical_form": "it",
      "relationship_kind": "LEMMA_FORM"
    },
    {
      "source_lexical_form": "itself",
      "target_lexical_form": "it",
      "relationship_kind": "LEMMA_FORM"
    },
    {
      "source_lexical_form": "us",
      "target_lexical_form": "we",
      "relationship_kind": "PRONOUN_SUBJECT_FORM"
    },
    {
      "source_lexical_form": "our",
      "target_lexical_form": "we",
      "relationship_kind": "LEMMA_FORM"
    },
    {
      "source_lexical_form": "ours",
      "target_lexical_form": "we",
      "relationship_kind": "LEMMA_FORM"
    },
    {
      "source_lexical_form": "ourselves",
      "target_lexical_form": "we",
      "relationship_kind": "LEMMA_FORM"
    },
    {
      "source_lexical_form": "them",
      "target_lexical_form": "they",
      "relationship_kind": "PRONOUN_SUBJECT_FORM"
    },
    {
      "source_lexical_form": "their",
      "target_lexical_form": "they",
      "relationship_kind": "LEMMA_FORM"
    },
    {
      "source_lexical_form": "theirs",
      "target_lexical_form": "they",
      "relationship_kind": "LEMMA_FORM"
    },
    {
      "source_lexical_form": "themselves",
      "target_lexical_form": "they",
      "relationship_kind": "LEMMA_FORM"
    },
    {
      "source_lexical_form": "done",
      "target_lexical_form": "do",
      "relationship_kind": "LEMMA_FORM"
    },
    {
      "source_lexical_form": "doing",
      "target_lexical_form": "do",
      "relationship_kind": "LEMMA_FORM"
    },
    {
      "source_lexical_form": "fewest",
      "target_lexical_form": "few",
      "relationship_kind": "LEMMA_FORM"
    },
    {
      "source_lexical_form": "less",
      "target_lexical_form": "little",
      "relationship_kind": "LEMMA_FORM"
    },
    {
      "source_lexical_form": "least",
      "target_lexical_form": "little",
      "relationship_kind": "LEMMA_FORM"
    },
    {
      "source_lexical_form": "relate",
      "target_lexical_form": "relating",
      "relationship_kind": "PRESENT_PARTICIPLE_FORM"
    },
    {
      "source_lexical_form": "relating",
      "target_lexical_form": "relate",
      "relationship_kind": "LEMMA_FORM"
    },
    {
      "source_lexical_form": "express",
      "target_lexical_form": "expressed",
      "relationship_kind": "PAST_PARTICIPLE_FORM"
    },
    {
      "source_lexical_form": "expressed",
      "target_lexical_form": "express",
      "relationship_kind": "LEMMA_FORM"
    },
    {
      "source_lexical_form": "common",
      "target_lexical_form": "commonly",
      "relationship_kind": "ADVERBIAL_DERIVATION"
    },
    {
      "source_lexical_form": "commonly",
      "target_lexical_form": "common",
      "relationship_kind": "LEMMA_FORM"
    },
    {
      "source_lexical_form": "compare",
      "target_lexical_form": "compared",
      "relationship_kind": "PAST_PARTICIPLE_FORM"
    },
    {
      "source_lexical_form": "compared",
      "target_lexical_form": "compare",
      "relationship_kind": "LEMMA_FORM"
    },
    {
      "source_lexical_form": "describe",
      "target_lexical_form": "described",
      "relationship_kind": "PAST_PARTICIPLE_FORM"
    },
    {
      "source_lexical_form": "described",
      "target_lexical_form": "describe",
      "relationship_kind": "LEMMA_FORM"
    },
    {
      "source_lexical_form": "determine",
      "target_lexical_form": "determined",
      "relationship_kind": "PAST_PARTICIPLE_FORM"
    },
    {
      "source_lexical_form": "determined",
      "target_lexical_form": "determine",
      "relationship_kind": "LEMMA_FORM"
    },
    {
      "source_lexical_form": "number",
      "target_lexical_form": "numbers",
      "relationship_kind": "PLURAL_FORM"
    },
    {
      "source_lexical_form": "numbers",
      "target_lexical_form": "number",
      "relationship_kind": "LEMMA_FORM"
    },
    {
      "source_lexical_form": "place",
      "target_lexical_form": "placed",
      "relationship_kind": "PAST_PARTICIPLE_FORM"
    },
    {
      "source_lexical_form": "placed",
      "target_lexical_form": "place",
      "relationship_kind": "LEMMA_FORM"
    },
    {
      "source_lexical_form": "position",
      "target_lexical_form": "positions",
      "relationship_kind": "PLURAL_FORM"
    },
    {
      "source_lexical_form": "positions",
      "target_lexical_form": "position",
      "relationship_kind": "LEMMA_FORM"
    },
    {
      "source_lexical_form": "quantity",
      "target_lexical_form": "quantities",
      "relationship_kind": "PLURAL_FORM"
    },
    {
      "source_lexical_form": "quantities",
      "target_lexical_form": "quantity",
      "relationship_kind": "LEMMA_FORM"
    },
    {
      "source_lexical_form": "represent",
      "target_lexical_form": "represents",
      "relationship_kind": "THIRD_PERSON_FORM"
    },
    {
      "source_lexical_form": "represents",
      "target_lexical_form": "represent",
      "relationship_kind": "LEMMA_FORM"
    },
    {
      "source_lexical_form": "result",
      "target_lexical_form": "resulting",
      "relationship_kind": "PRESENT_PARTICIPLE_FORM"
    },
    {
      "source_lexical_form": "resulting",
      "target_lexical_form": "result",
      "relationship_kind": "LEMMA_FORM"
    },
    {
      "source_lexical_form": "change",
      "target_lexical_form": "changes",
      "relationship_kind": "THIRD_PERSON_FORM"
    },
    {
      "source_lexical_form": "changes",
      "target_lexical_form": "change",
      "relationship_kind": "LEMMA_FORM"
    },
    {
      "source_lexical_form": "change",
      "target_lexical_form": "changing",
      "relationship_kind": "PRESENT_PARTICIPLE_FORM"
    },
    {
      "source_lexical_form": "changing",
      "target_lexical_form": "change",
      "relationship_kind": "LEMMA_FORM"
    },
    {
      "source_lexical_form": "continuous",
      "target_lexical_form": "continuously",
      "relationship_kind": "ADVERBIAL_DERIVATION"
    },
    {
      "source_lexical_form": "continuously",
      "target_lexical_form": "continuous",
      "relationship_kind": "LEMMA_FORM"
    },
    {
      "source_lexical_form": "effect",
      "target_lexical_form": "effects",
      "relationship_kind": "PLURAL_FORM"
    },
    {
      "source_lexical_form": "effects",
      "target_lexical_form": "effect",
      "relationship_kind": "LEMMA_FORM"
    },
    {
      "source_lexical_form": "happen",
      "target_lexical_form": "happening",
      "relationship_kind": "PRESENT_PARTICIPLE_FORM"
    },
    {
      "source_lexical_form": "happening",
      "target_lexical_form": "happen",
      "relationship_kind": "LEMMA_FORM"
    },
    {
      "source_lexical_form": "increase",
      "target_lexical_form": "increases",
      "relationship_kind": "THIRD_PERSON_FORM"
    },
    {
      "source_lexical_form": "increases",
      "target_lexical_form": "increase",
      "relationship_kind": "LEMMA_FORM"
    },
    {
      "source_lexical_form": "make",
      "target_lexical_form": "makes",
      "relationship_kind": "THIRD_PERSON_FORM"
    },
    {
      "source_lexical_form": "makes",
      "target_lexical_form": "make",
      "relationship_kind": "LEMMA_FORM"
    },
    {
      "source_lexical_form": "measure",
      "target_lexical_form": "measured",
      "relationship_kind": "PAST_PARTICIPLE_FORM"
    },
    {
      "source_lexical_form": "measured",
      "target_lexical_form": "measure",
      "relationship_kind": "LEMMA_FORM"
    },
    {
      "source_lexical_form": "part",
      "target_lexical_form": "parts",
      "relationship_kind": "PLURAL_FORM"
    },
    {
      "source_lexical_form": "parts",
      "target_lexical_form": "part",
      "relationship_kind": "LEMMA_FORM"
    },
    {
      "source_lexical_form": "relation",
      "target_lexical_form": "relations",
      "relationship_kind": "PLURAL_FORM"
    },
    {
      "source_lexical_form": "relations",
      "target_lexical_form": "relation",
      "relationship_kind": "LEMMA_FORM"
    },
    {
      "source_lexical_form": "steady",
      "target_lexical_form": "steadily",
      "relationship_kind": "ADVERBIAL_DERIVATION"
    },
    {
      "source_lexical_form": "steadily",
      "target_lexical_form": "steady",
      "relationship_kind": "LEMMA_FORM"
    },
    {
      "source_lexical_form": "store",
      "target_lexical_form": "stored",
      "relationship_kind": "PAST_PARTICIPLE_FORM"
    },
    {
      "source_lexical_form": "stored",
      "target_lexical_form": "store",
      "relationship_kind": "LEMMA_FORM"
    },
    {
      "source_lexical_form": "achieve",
      "target_lexical_form": "achievement",
      "relationship_kind": "NOMINALISATION"
    },
    {
      "source_lexical_form": "achievement",
      "target_lexical_form": "achieve",
      "relationship_kind": "LEMMA_FORM"
    },
    {
      "source_lexical_form": "add",
      "target_lexical_form": "addition",
      "relationship_kind": "NOMINALISATION"
    },
    {
      "source_lexical_form": "addition",
      "target_lexical_form": "add",
      "relationship_kind": "LEMMA_FORM"
    },
    {
      "source_lexical_form": "appear",
      "target_lexical_form": "appearance",
      "relationship_kind": "NOMINALISATION"
    },
    {
      "source_lexical_form": "appearance",
      "target_lexical_form": "appear",
      "relationship_kind": "LEMMA_FORM"
    },
    {
      "source_lexical_form": "assemble",
      "target_lexical_form": "assembly",
      "relationship_kind": "NOMINALISATION"
    },
    {
      "source_lexical_form": "assembly",
      "target_lexical_form": "assemble",
      "relationship_kind": "LEMMA_FORM"
    },
    {
      "source_lexical_form": "assign",
      "target_lexical_form": "assignment",
      "relationship_kind": "NOMINALISATION"
    },
    {
      "source_lexical_form": "assignment",
      "target_lexical_form": "assign",
      "relationship_kind": "LEMMA_FORM"
    },
    {
      "source_lexical_form": "choose",
      "target_lexical_form": "choice",
      "relationship_kind": "NOMINALISATION"
    },
    {
      "source_lexical_form": "choice",
      "target_lexical_form": "choose",
      "relationship_kind": "LEMMA_FORM"
    },
    {
      "source_lexical_form": "combine",
      "target_lexical_form": "combination",
      "relationship_kind": "NOMINALISATION"
    },
    {
      "source_lexical_form": "combination",
      "target_lexical_form": "combine",
      "relationship_kind": "LEMMA_FORM"
    },
    {
      "source_lexical_form": "compare",
      "target_lexical_form": "comparison",
      "relationship_kind": "NOMINALISATION"
    },
    {
      "source_lexical_form": "comparison",
      "target_lexical_form": "compare",
      "relationship_kind": "LEMMA_FORM"
    },
    {
      "source_lexical_form": "connect",
      "target_lexical_form": "connection",
      "relationship_kind": "NOMINALISATION"
    },
    {
      "source_lexical_form": "connection",
      "target_lexical_form": "connect",
      "relationship_kind": "LEMMA_FORM"
    },
    {
      "source_lexical_form": "depend",
      "target_lexical_form": "dependence",
      "relationship_kind": "NOMINALISATION"
    },
    {
      "source_lexical_form": "dependence",
      "target_lexical_form": "depend",
      "relationship_kind": "LEMMA_FORM"
    },
    {
      "source_lexical_form": "describe",
      "target_lexical_form": "description",
      "relationship_kind": "NOMINALISATION"
    },
    {
      "source_lexical_form": "description",
      "target_lexical_form": "describe",
      "relationship_kind": "LEMMA_FORM"
    },
    {
      "source_lexical_form": "determine",
      "target_lexical_form": "determination",
      "relationship_kind": "NOMINALISATION"
    },
    {
      "source_lexical_form": "determination",
      "target_lexical_form": "determine",
      "relationship_kind": "LEMMA_FORM"
    },
    {
      "source_lexical_form": "develop",
      "target_lexical_form": "development",
      "relationship_kind": "NOMINALISATION"
    },
    {
      "source_lexical_form": "development",
      "target_lexical_form": "develop",
      "relationship_kind": "LEMMA_FORM"
    },
    {
      "source_lexical_form": "divide",
      "target_lexical_form": "division",
      "relationship_kind": "NOMINALISATION"
    },
    {
      "source_lexical_form": "division",
      "target_lexical_form": "divide",
      "relationship_kind": "LEMMA_FORM"
    },
    {
      "source_lexical_form": "exclude",
      "target_lexical_form": "exclusion",
      "relationship_kind": "NOMINALISATION"
    },
    {
      "source_lexical_form": "exclusion",
      "target_lexical_form": "exclude",
      "relationship_kind": "LEMMA_FORM"
    },
    {
      "source_lexical_form": "express",
      "target_lexical_form": "expression",
      "relationship_kind": "NOMINALISATION"
    },
    {
      "source_lexical_form": "expression",
      "target_lexical_form": "express",
      "relationship_kind": "LEMMA_FORM"
    },
    {
      "source_lexical_form": "gather",
      "target_lexical_form": "gathering",
      "relationship_kind": "NOMINALISATION"
    },
    {
      "source_lexical_form": "gathering",
      "target_lexical_form": "gather",
      "relationship_kind": "LEMMA_FORM"
    },
    {
      "source_lexical_form": "identify",
      "target_lexical_form": "identification",
      "relationship_kind": "NOMINALISATION"
    },
    {
      "source_lexical_form": "identification",
      "target_lexical_form": "identify",
      "relationship_kind": "LEMMA_FORM"
    },
    {
      "source_lexical_form": "include",
      "target_lexical_form": "inclusion",
      "relationship_kind": "NOMINALISATION"
    },
    {
      "source_lexical_form": "inclusion",
      "target_lexical_form": "include",
      "relationship_kind": "LEMMA_FORM"
    },
    {
      "source_lexical_form": "indicate",
      "target_lexical_form": "indication",
      "relationship_kind": "NOMINALISATION"
    },
    {
      "source_lexical_form": "indication",
      "target_lexical_form": "indicate",
      "relationship_kind": "LEMMA_FORM"
    },
    {
      "source_lexical_form": "locate",
      "target_lexical_form": "location",
      "relationship_kind": "NOMINALISATION"
    },
    {
      "source_lexical_form": "location",
      "target_lexical_form": "locate",
      "relationship_kind": "LEMMA_FORM"
    },
    {
      "source_lexical_form": "manifest",
      "target_lexical_form": "manifestation",
      "relationship_kind": "NOMINALISATION"
    },
    {
      "source_lexical_form": "manifestation",
      "target_lexical_form": "manifest",
      "relationship_kind": "LEMMA_FORM"
    },
    {
      "source_lexical_form": "modify",
      "target_lexical_form": "modification",
      "relationship_kind": "NOMINALISATION"
    },
    {
      "source_lexical_form": "modification",
      "target_lexical_form": "modify",
      "relationship_kind": "LEMMA_FORM"
    },
    {
      "source_lexical_form": "move",
      "target_lexical_form": "movement",
      "relationship_kind": "NOMINALISATION"
    },
    {
      "source_lexical_form": "movement",
      "target_lexical_form": "move",
      "relationship_kind": "LEMMA_FORM"
    },
    {
      "source_lexical_form": "multiply",
      "target_lexical_form": "multiplication",
      "relationship_kind": "NOMINALISATION"
    },
    {
      "source_lexical_form": "multiplication",
      "target_lexical_form": "multiply",
      "relationship_kind": "LEMMA_FORM"
    },
    {
      "source_lexical_form": "pass",
      "target_lexical_form": "passage",
      "relationship_kind": "NOMINALISATION"
    },
    {
      "source_lexical_form": "passage",
      "target_lexical_form": "pass",
      "relationship_kind": "LEMMA_FORM"
    },
    {
      "source_lexical_form": "perform",
      "target_lexical_form": "performance",
      "relationship_kind": "NOMINALISATION"
    },
    {
      "source_lexical_form": "performance",
      "target_lexical_form": "perform",
      "relationship_kind": "LEMMA_FORM"
    },
    {
      "source_lexical_form": "precede",
      "target_lexical_form": "precedence",
      "relationship_kind": "NOMINALISATION"
    },
    {
      "source_lexical_form": "precedence",
      "target_lexical_form": "precede",
      "relationship_kind": "LEMMA_FORM"
    },
    {
      "source_lexical_form": "qualify",
      "target_lexical_form": "qualification",
      "relationship_kind": "NOMINALISATION"
    },
    {
      "source_lexical_form": "qualification",
      "target_lexical_form": "qualify",
      "relationship_kind": "LEMMA_FORM"
    },
    {
      "source_lexical_form": "refer",
      "target_lexical_form": "reference",
      "relationship_kind": "NOMINALISATION"
    },
    {
      "source_lexical_form": "reference",
      "target_lexical_form": "refer",
      "relationship_kind": "LEMMA_FORM"
    },
    {
      "source_lexical_form": "relate",
      "target_lexical_form": "relation",
      "relationship_kind": "NOMINALISATION"
    },
    {
      "source_lexical_form": "relation",
      "target_lexical_form": "relate",
      "relationship_kind": "LEMMA_FORM"
    },
    {
      "source_lexical_form": "replace",
      "target_lexical_form": "replacement",
      "relationship_kind": "NOMINALISATION"
    },
    {
      "source_lexical_form": "replacement",
      "target_lexical_form": "replace",
      "relationship_kind": "LEMMA_FORM"
    },
    {
      "source_lexical_form": "represent",
      "target_lexical_form": "representation",
      "relationship_kind": "NOMINALISATION"
    },
    {
      "source_lexical_form": "representation",
      "target_lexical_form": "represent",
      "relationship_kind": "LEMMA_FORM"
    },
    {
      "source_lexical_form": "specify",
      "target_lexical_form": "specification",
      "relationship_kind": "NOMINALISATION"
    },
    {
      "source_lexical_form": "specification",
      "target_lexical_form": "specify",
      "relationship_kind": "LEMMA_FORM"
    },
    {
      "source_lexical_form": "store",
      "target_lexical_form": "storage",
      "relationship_kind": "NOMINALISATION"
    },
    {
      "source_lexical_form": "storage",
      "target_lexical_form": "store",
      "relationship_kind": "LEMMA_FORM"
    },
    {
      "source_lexical_form": "subtract",
      "target_lexical_form": "subtraction",
      "relationship_kind": "NOMINALISATION"
    },
    {
      "source_lexical_form": "subtraction",
      "target_lexical_form": "subtract",
      "relationship_kind": "LEMMA_FORM"
    },
    {
      "source_lexical_form": "occur",
      "target_lexical_form": "occurrence",
      "relationship_kind": "NOMINALISATION"
    },
    {
      "source_lexical_form": "occurrence",
      "target_lexical_form": "occur",
      "relationship_kind": "LEMMA_FORM"
    },
    {
      "source_lexical_form": "produce",
      "target_lexical_form": "production",
      "relationship_kind": "NOMINALISATION"
    },
    {
      "source_lexical_form": "production",
      "target_lexical_form": "produce",
      "relationship_kind": "LEMMA_FORM"
    },
    {
      "source_lexical_form": "introduce",
      "target_lexical_form": "introduction",
      "relationship_kind": "NOMINALISATION"
    },
    {
      "source_lexical_form": "introduction",
      "target_lexical_form": "introduce",
      "relationship_kind": "LEMMA_FORM"
    },
    {
      "source_lexical_form": "contain",
      "target_lexical_form": "containment",
      "relationship_kind": "NOMINALISATION"
    },
    {
      "source_lexical_form": "containment",
      "target_lexical_form": "contain",
      "relationship_kind": "LEMMA_FORM"
    },
    {
      "source_lexical_form": "accompany",
      "target_lexical_form": "accompaniment",
      "relationship_kind": "NOMINALISATION"
    },
    {
      "source_lexical_form": "accompaniment",
      "target_lexical_form": "accompany",
      "relationship_kind": "LEMMA_FORM"
    },
    {
      "source_lexical_form": "receive",
      "target_lexical_form": "reception",
      "relationship_kind": "NOMINALISATION"
    },
    {
      "source_lexical_form": "reception",
      "target_lexical_form": "receive",
      "relationship_kind": "LEMMA_FORM"
    },
    {
      "source_lexical_form": "occur",
      "target_lexical_form": "occurs",
      "relationship_kind": "THIRD_PERSON_FORM"
    },
    {
      "source_lexical_form": "occurs",
      "target_lexical_form": "occur",
      "relationship_kind": "LEMMA_FORM"
    }
  ]
}
